vectorvfs/__init__.py
vectorvfs/cli.py
vectorvfs/encoders.py
vectorvfs/utils.py
vectorvfs/vfsstore.py
vectorvfs-0.3.0.dist-info/licenses/LICENSE
vectorvfs-0.3.0.dist-info/METADATA
vectorvfs-0.3.0.dist-info/WHEEL
vectorvfs-0.3.0.dist-info/entry_points.txt
vectorvfs-0.3.0.dist-info/top_level.txt
vectorvfs-0.3.0.dist-info/RECORD
