Metadata-Version: 2.4
Name: vectorvfs
Version: 0.3.0
Summary: Your filesystem is a vector database.
Project-URL: Homepage, https://github.com/perone/vectorvfs
Project-URL: Issues, https://github.com/perone/vectorvfs/issues
Requires-Python: >=3.12
License-File: LICENSE
Requires-Dist: click>=8.1.8
Requires-Dist: perception-models-perone>=1.0.0
Requires-Dist: pillow>=11.0.0
Requires-Dist: rich>=14.0.0
Requires-Dist: torch==2.5.1
Requires-Dist: torchaudio==2.5.1
Requires-Dist: torchcodec==0.1
Requires-Dist: torchvision==0.20.1
Requires-Dist: xformers>=0.0.29.post1
Dynamic: license-file
